mailoxy/__init__.py
mailoxy/aes.pyd
mailoxy/db_types.pyd
mailoxy/dmr.py
mailoxy/errors.py
mailoxy/mai2.pyd
mailoxy/maihttp.pyd
mailoxy/maimanager.pyd
mailoxy/maitypes.py
mailoxy/other.py
mailoxy/resmanager.py
mailoxy/userid.pyd
mailoxy-1.0.1.dist-info/METADATA
mailoxy-1.0.1.dist-info/WHEEL
mailoxy-1.0.1.dist-info/top_level.txt
mailoxy-1.0.1.dist-info/RECORD
