Metadata-Version: 2.1
Name: mailoxy
Version: 1.0.1
Summary: maimai llc tool box
Author: llc
Author-email: gllc153220@gmail.com
License: Mozilla Public License
Platform: windows
Requires-Dist: httpx
Requires-Dist: crypto
Requires-Dist: pycryptodome
Requires-Dist: orjson
Requires-Dist: h2
Requires-Dist: pydantic
Requires-Dist: Loguru
Requires-Dist: UnityPy
Requires-Dist: Pillow
